{
  "scene": "triangle_stroke_fill",
  "duration": 6,
  "fps": 30,
  "canvas": {
    "w": 1920,
    "h": 1080
  },
  "bg": "#000000",
  "objects": [
    {
      "id": "triangle_1",
      "shape": "triangle",
      "size": [
        195,
        195
      ],
      "stroke": {
        "color": "#FFFFFF",
        "width": 4
      },
      "fill": false,
      "pos": [
        0,
        0
      ],
      "opacity": 1
    }
  ],
  "timeline": [
    {
      "target": "triangle_1",
      "time": [
        0,
        2
      ],
      "rotation": [
        0,
        360
      ]
    },
    {
      "target": "triangle_1",
      "time": [
        2,
        4
      ],
      "color": [
        "transparent",
        "#FDD835"
      ]
    },
    {
      "target": "triangle_1",
      "time": [
        4,
        6
      ],
      "stroke": {
        "color": [
          "#FFFFFF",
          "transparent"
        ]
      }
    }
  ]
}